lslgwlib/__init__.py
lslgwlib/enums/__init__.py
lslgwlib/enums/attach_point.py
lslgwlib/enums/change.py
lslgwlib/enums/chatchannel.py
lslgwlib/enums/inventory.py
lslgwlib/enums/linknum.py
lslgwlib/enums/permissions.py
lslgwlib/models/__init__.py
lslgwlib/models/avatar.py
lslgwlib/models/chatmessage.py
lslgwlib/models/httpdata.py
lslgwlib/models/inventory.py
lslgwlib/models/linkmessage.py
lslgwlib/models/linksetinfo.py
lslgwlib/models/money.py
lslgwlib/models/permissions.py
lslgwlib/models/priminfo.py
lslgwlib/models/region.py
lslgwlib/models/touch.py
lslgwlib/py.typed
lsl_gateway_lib-24.8.0.dist-info/LICENSE-lgpl-3.0.md
lsl_gateway_lib-24.8.0.dist-info/METADATA
lsl_gateway_lib-24.8.0.dist-info/WHEEL
lsl_gateway_lib-24.8.0.dist-info/RECORD
