Metadata-Version: 2.1
Name: lsl-gateway-lib
Version: 24.8.0
Summary: Gateway from Python to LSL in Second Life - library
License: LGPL-3.0-or-later
Author: erfea
Author-email: erfea.tux@gmail.com
Requires-Python: >=3.10,<4.0
Classifier: License :: OSI Approved :: GNU Lesser General Public License v3 or later (LGPLv3+)
Classifier: Programming Language :: Python :: 3
Classifier: Programming Language :: Python :: 3.10
Classifier: Programming Language :: Python :: 3.11
Classifier: Programming Language :: Python :: 3.12
Requires-Dist: pydantic (>=2.8.2,<3.0.0)
